odoo8_addon_mgmtsystem_hazard_risk-8.0.1.1.0.99.dev16-py2.7-nspkg.pth
odoo8_addon_mgmtsystem_hazard_risk-8.0.1.1.0.99.dev16.dist-info/DESCRIPTION.rst
odoo8_addon_mgmtsystem_hazard_risk-8.0.1.1.0.99.dev16.dist-info/METADATA
odoo8_addon_mgmtsystem_hazard_risk-8.0.1.1.0.99.dev16.dist-info/RECORD
odoo8_addon_mgmtsystem_hazard_risk-8.0.1.1.0.99.dev16.dist-info/WHEEL
odoo8_addon_mgmtsystem_hazard_risk-8.0.1.1.0.99.dev16.dist-info/metadata.json
odoo8_addon_mgmtsystem_hazard_risk-8.0.1.1.0.99.dev16.dist-info/namespace_packages.txt
odoo8_addon_mgmtsystem_hazard_risk-8.0.1.1.0.99.dev16.dist-info/top_level.txt
odoo_addons/mgmtsystem_hazard_risk/README.rst
odoo_addons/mgmtsystem_hazard_risk/__init__.py
odoo_addons/mgmtsystem_hazard_risk/__openerp__.py
odoo_addons/mgmtsystem_hazard_risk/data/mgmtsystem_hazard_risk_computation.xml
odoo_addons/mgmtsystem_hazard_risk/data/mgmtsystem_hazard_risk_type.xml
odoo_addons/mgmtsystem_hazard_risk/i18n/de.po
odoo_addons/mgmtsystem_hazard_risk/i18n/es.po
odoo_addons/mgmtsystem_hazard_risk/i18n/fr.po
odoo_addons/mgmtsystem_hazard_risk/i18n/hr.po
odoo_addons/mgmtsystem_hazard_risk/i18n/id.po
odoo_addons/mgmtsystem_hazard_risk/i18n/mgmtsystem_hazard_risk.pot
odoo_addons/mgmtsystem_hazard_risk/i18n/nb.po
odoo_addons/mgmtsystem_hazard_risk/i18n/pt_BR.po
odoo_addons/mgmtsystem_hazard_risk/i18n/sl.po
odoo_addons/mgmtsystem_hazard_risk/i18n/vi.po
odoo_addons/mgmtsystem_hazard_risk/models/__init__.py
odoo_addons/mgmtsystem_hazard_risk/models/common.py
odoo_addons/mgmtsystem_hazard_risk/models/mgmtsystem_hazard.py
odoo_addons/mgmtsystem_hazard_risk/models/mgmtsystem_hazard_residual_risk.py
odoo_addons/mgmtsystem_hazard_risk/models/mgmtsystem_hazard_risk_computation.py
odoo_addons/mgmtsystem_hazard_risk/models/mgmtsystem_hazard_risk_type.py
odoo_addons/mgmtsystem_hazard_risk/models/res_company.py
odoo_addons/mgmtsystem_hazard_risk/security/ir.model.access.csv
odoo_addons/mgmtsystem_hazard_risk/security/mgmtsystem_hazard_security.xml
odoo_addons/mgmtsystem_hazard_risk/static/description/icon.png
odoo_addons/mgmtsystem_hazard_risk/tests/__init__.py
odoo_addons/mgmtsystem_hazard_risk/tests/test_mgmtsystem_hazard.py
odoo_addons/mgmtsystem_hazard_risk/views/mgmtsystem_hazard.xml
odoo_addons/mgmtsystem_hazard_risk/views/mgmtsystem_hazard_residual_risk.xml
odoo_addons/mgmtsystem_hazard_risk/views/mgmtsystem_hazard_risk_computation.xml
odoo_addons/mgmtsystem_hazard_risk/views/mgmtsystem_hazard_risk_type.xml
